borica/__init__.py
borica/request.py
borica/response.py
borica/signature.py
borica/verifier.py
borica/scripts/__init__.py
borica/scripts/cli.py
borica-0.0.1.dev0.dist-info/DESCRIPTION.rst
borica-0.0.1.dev0.dist-info/METADATA
borica-0.0.1.dev0.dist-info/RECORD
borica-0.0.1.dev0.dist-info/WHEEL
borica-0.0.1.dev0.dist-info/entry_points.txt
borica-0.0.1.dev0.dist-info/metadata.json
borica-0.0.1.dev0.dist-info/top_level.txt
borica-0.0.1.dev0.dist-info/zip-safe
